{"RESULT": {"OIL":[ {"SIGUNCD":"0902","SIGUNNM":"경남 창원시","PRODCD":"B027","PRICE":1628.24,"DIFF":0.68}, {"SIGUNCD":"0902","SIGUNNM":"경남 창원시","PRODCD":"B034","PRICE":1851.00,"DIFF":-2.07}, {"SIGUNCD":"0902","SIGUNNM":"경남 창원시","PRODCD":"C004","PRICE":1407.26,"DIFF":0.71}, {"SIGUNCD":"0902","SIGUNNM":"경남 창원시","PRODCD":"D047","PRICE":1475.19,"DIFF":1.84}, {"SIGUNCD":"0902","SIGUNNM":"경남 창원시","PRODCD":"K015","PRICE":1004.56,"DIFF":0.00}, {"SIGUNCD":"0904","SIGUNNM":"경남 진주시","PRODCD":"B027","PRICE":1617.21,"DIFF":1.00}, {"SIGUNCD":"0904","SIGUNNM":"경남 진주시","PRODCD":"B034","PRICE":1835.15,"DIFF":0.77}, {"SIGUNCD":"0904","SIGUNNM":"경남 진주시","PRODCD":"C004","PRICE":1322.79,"DIFF":0.00}, {"SIGUNCD":"0904","SIGUNNM":"경남 진주시","PRODCD":"D047","PRICE":1468.82,"DIFF":1.91}, {"SIGUNCD":"0904","SIGUNNM":"경남 진주시","PRODCD":"K015","PRICE":1042.55,"DIFF":0.00}, {"SIGUNCD":"0906","SIGUNNM":"경남 통영시","PRODCD":"B027","PRICE":1629.67,"DIFF":0.50}, {"SIGUNCD":"0906","SIGUNNM":"경남 통영시","PRODCD":"B034","PRICE":1842.25,"DIFF":0.00}, {"SIGUNCD":"0906","SIGUNNM":"경남 통영시","PRODCD":"C004","PRICE":1349.69,"DIFF":0.31}, {"SIGUNCD":"0906","SIGUNNM":"경남 통영시","PRODCD":"D047","PRICE":1497.27,"DIFF":2.10}, {"SIGUNCD":"0906","SIGUNNM":"경남 통영시","PRODCD":"K015","PRICE":1039.67,"DIFF":0.00}, {"SIGUNCD":"0907","SIGUNNM":"경남 사천시","PRODCD":"B027","PRICE":1599.21,"DIFF":1.04}, {"SIGUNCD":"0907","SIGUNNM":"경남 사천시","PRODCD":"B034","PRICE":1878.67,"DIFF":0.00}, {"SIGUNCD":"0907","SIGUNNM":"경남 사천시","PRODCD":"C004","PRICE":1305.44,"DIFF":-1.47}, {"SIGUNCD":"0907","SIGUNNM":"경남 사천시","PRODCD":"D047","PRICE":1460.00,"DIFF":0.83}, {"SIGUNCD":"0907","SIGUNNM":"경남 사천시","PRODCD":"K015","PRICE":1012.31,"DIFF":0.00}, {"SIGUNCD":"0908","SIGUNNM":"경남 김해시","PRODCD":"B027","PRICE":1637.01,"DIFF":1.08}, {"SIGUNCD":"0908","SIGUNNM":"경남 김해시","PRODCD":"B034","PRICE":1844.07,"DIFF":3.28}, {"SIGUNCD":"0908","SIGUNNM":"경남 김해시","PRODCD":"C004","PRICE":1386.36,"DIFF":1.10}, {"SIGUNCD":"0908","SIGUNNM":"경남 김해시","PRODCD":"D047","PRICE":1472.48,"DIFF":0.83}, {"SIGUNCD":"0908","SIGUNNM":"경남 김해시","PRODCD":"K015","PRICE":1006.45,"DIFF":0.00}, {"SIGUNCD":"0909","SIGUNNM":"경남 밀양시","PRODCD":"B027","PRICE":1644.85,"DIFF":1.27}, {"SIGUNCD":"0909","SIGUNNM":"경남 밀양시","PRODCD":"B034","PRICE":1929.00,"DIFF":0.00}, {"SIGUNCD":"0909","SIGUNNM":"경남 밀양시","PRODCD":"C004","PRICE":1303.09,"DIFF":0.00}, {"SIGUNCD":"0909","SIGUNNM":"경남 밀양시","PRODCD":"D047","PRICE":1476.67,"DIFF":2.18}, {"SIGUNCD":"0909","SIGUNNM":"경남 밀양시","PRODCD":"K015","PRICE":1064.00,"DIFF":0.00}, {"SIGUNCD":"0910","SIGUNNM":"경남 거제시","PRODCD":"B027","PRICE":1648.90,"DIFF":1.08}, {"SIGUNCD":"0910","SIGUNNM":"경남 거제시","PRODCD":"B034","PRICE":1808.33,"DIFF":0.00}, {"SIGUNCD":"0910","SIGUNNM":"경남 거제시","PRODCD":"C004","PRICE":1357.14,"DIFF":-1.43}, {"SIGUNCD":"0910","SIGUNNM":"경남 거제시","PRODCD":"D047","PRICE":1521.56,"DIFF":0.60}, {"SIGUNCD":"0910","SIGUNNM":"경남 거제시","PRODCD":"K015","PRICE":1054.75,"DIFF":0.00}, {"SIGUNCD":"0911","SIGUNNM":"경남 양산시","PRODCD":"B027","PRICE":1632.21,"DIFF":0.77}, {"SIGUNCD":"0911","SIGUNNM":"경남 양산시","PRODCD":"B034","PRICE":1903.10,"DIFF":3.00}, {"SIGUNCD":"0911","SIGUNNM":"경남 양산시","PRODCD":"C004","PRICE":1359.71,"DIFF":1.47}, {"SIGUNCD":"0911","SIGUNNM":"경남 양산시","PRODCD":"D047","PRICE":1473.59,"DIFF":2.71}, {"SIGUNCD":"0911","SIGUNNM":"경남 양산시","PRODCD":"K015","PRICE":1048.47,"DIFF":0.00}, {"SIGUNCD":"0922","SIGUNNM":"경남 의령군","PRODCD":"B027","PRICE":1658.41,"DIFF":0.00}, {"SIGUNCD":"0922","SIGUNNM":"경남 의령군","PRODCD":"C004","PRICE":1267.86,"DIFF":3.57}, {"SIGUNCD":"0922","SIGUNNM":"경남 의령군","PRODCD":"D047","PRICE":1498.12,"DIFF":0.00}, {"SIGUNCD":"0922","SIGUNNM":"경남 의령군","PRODCD":"K015","PRICE":1045.00,"DIFF":0.00}, {"SIGUNCD":"0923","SIGUNNM":"경남 함안군","PRODCD":"B027","PRICE":1622.87,"DIFF":0.12}, {"SIGUNCD":"0923","SIGUNNM":"경남 함안군","PRODCD":"B034","PRICE":1902.50,"DIFF":12.50}, {"SIGUNCD":"0923","SIGUNNM":"경남 함안군","PRODCD":"C004","PRICE":1309.49,"DIFF":-1.22}, {"SIGUNCD":"0923","SIGUNNM":"경남 함안군","PRODCD":"D047","PRICE":1459.83,"DIFF":1.47}, {"SIGUNCD":"0923","SIGUNNM":"경남 함안군","PRODCD":"K015","PRICE":1063.11,"DIFF":0.00}, {"SIGUNCD":"0924","SIGUNNM":"경남 창녕군","PRODCD":"B027","PRICE":1630.73,"DIFF":0.63}, {"SIGUNCD":"0924","SIGUNNM":"경남 창녕군","PRODCD":"B034","PRICE":1795.00,"DIFF":0.00}, {"SIGUNCD":"0924","SIGUNNM":"경남 창녕군","PRODCD":"C004","PRICE":1280.26,"DIFF":2.05}, {"SIGUNCD":"0924","SIGUNNM":"경남 창녕군","PRODCD":"D047","PRICE":1467.45,"DIFF":1.63}, {"SIGUNCD":"0924","SIGUNNM":"경남 창녕군","PRODCD":"K015","PRICE":1024.86,"DIFF":4.72}, {"SIGUNCD":"0932","SIGUNNM":"경남 고성군","PRODCD":"B027","PRICE":1617.30,"DIFF":0.00}, {"SIGUNCD":"0932","SIGUNNM":"경남 고성군","PRODCD":"B034","PRICE":1995.00,"DIFF":0.00}, {"SIGUNCD":"0932","SIGUNNM":"경남 고성군","PRODCD":"C004","PRICE":1295.45,"DIFF":0.00}, {"SIGUNCD":"0932","SIGUNNM":"경남 고성군","PRODCD":"D047","PRICE":1473.10,"DIFF":0.67}, {"SIGUNCD":"0932","SIGUNNM":"경남 고성군","PRODCD":"K015","PRICE":1013.88,"DIFF":0.00}, {"SIGUNCD":"0934","SIGUNNM":"경남 남해군","PRODCD":"B027","PRICE":1657.27,"DIFF":3.18}, {"SIGUNCD":"0934","SIGUNNM":"경남 남해군","PRODCD":"C004","PRICE":1300.00,"DIFF":0.00}, {"SIGUNCD":"0934","SIGUNNM":"경남 남해군","PRODCD":"D047","PRICE":1517.27,"DIFF":3.63}, {"SIGUNCD":"0934","SIGUNNM":"경남 남해군","PRODCD":"K015","PRICE":1070.75,"DIFF":0.00}, {"SIGUNCD":"0935","SIGUNNM":"경남 하동군","PRODCD":"B027","PRICE":1643.63,"DIFF":0.32}, {"SIGUNCD":"0935","SIGUNNM":"경남 하동군","PRODCD":"C004","PRICE":1257.86,"DIFF":-0.71}, {"SIGUNCD":"0935","SIGUNNM":"경남 하동군","PRODCD":"D047","PRICE":1474.97,"DIFF":1.72}, {"SIGUNCD":"0935","SIGUNNM":"경남 하동군","PRODCD":"K015","PRICE":1056.00,"DIFF":0.00}, {"SIGUNCD":"0936","SIGUNNM":"경남 산청군","PRODCD":"B027","PRICE":1626.88,"DIFF":0.61}, {"SIGUNCD":"0936","SIGUNNM":"경남 산청군","PRODCD":"C004","PRICE":1205.24,"DIFF":-4.14}, {"SIGUNCD":"0936","SIGUNNM":"경남 산청군","PRODCD":"D047","PRICE":1471.94,"DIFF":1.25}, {"SIGUNCD":"0936","SIGUNNM":"경남 산청군","PRODCD":"K015","PRICE":1056.75,"DIFF":0.00}, {"SIGUNCD":"0937","SIGUNNM":"경남 함양군","PRODCD":"B027","PRICE":1636.96,"DIFF":0.77}, {"SIGUNCD":"0937","SIGUNNM":"경남 함양군","PRODCD":"C004","PRICE":1211.30,"DIFF":0.00}, {"SIGUNCD":"0937","SIGUNNM":"경남 함양군","PRODCD":"D047","PRICE":1469.74,"DIFF":-1.11}, {"SIGUNCD":"0937","SIGUNNM":"경남 함양군","PRODCD":"K015","PRICE":1051.60,"DIFF":0.00}, {"SIGUNCD":"0938","SIGUNNM":"경남 거창군","PRODCD":"B027","PRICE":1649.21,"DIFF":0.00}, {"SIGUNCD":"0938","SIGUNNM":"경남 거창군","PRODCD":"B034","PRICE":1992.00,"DIFF":0.00}, {"SIGUNCD":"0938","SIGUNNM":"경남 거창군","PRODCD":"C004","PRICE":1196.00,"DIFF":0.00}, {"SIGUNCD":"0938","SIGUNNM":"경남 거창군","PRODCD":"D047","PRICE":1498.14,"DIFF":-0.07}, {"SIGUNCD":"0938","SIGUNNM":"경남 거창군","PRODCD":"K015","PRICE":1097.00,"DIFF":0.00}, {"SIGUNCD":"0939","SIGUNNM":"경남 합천군","PRODCD":"B027","PRICE":1654.11,"DIFF":0.00}, {"SIGUNCD":"0939","SIGUNNM":"경남 합천군","PRODCD":"C004","PRICE":1288.85,"DIFF":0.00}, {"SIGUNCD":"0939","SIGUNNM":"경남 합천군","PRODCD":"D047","PRICE":1500.39,"DIFF":2.46}, {"SIGUNCD":"0939","SIGUNNM":"경남 합천군","PRODCD":"K015","PRICE":1090.50,"DIFF":0.00} ]} }